nzrec/__init__.py
nzrec/main.py
nzrec/shp_to_blt.py
nzrec/utils.py
nzrec/datasets/__init__.py
nzrec/tests/__init__.py
nzrec/tests/create_test_data.py
nzrec/tests/test_hdf5tools.py
nzrec-0.1.0.dist-info/METADATA
nzrec-0.1.0.dist-info/WHEEL
nzrec-0.1.0.dist-info/licenses/LICENSE
nzrec-0.1.0.dist-info/RECORD
