Metadata-Version: 2.4
Name: nzrec
Version: 0.1.0
Summary: NZ REC delineation tool
Project-URL: Homepage, https://github.com/mullenkamp/nzrec
Author-email: Mike Kittridge <mullenkamp1@gmail.com>
License-Expression: Apache-2.0
License-File: LICENSE
Keywords: rivers
Classifier: Development Status :: 3 - Alpha
Classifier: Intended Audience :: Developers
Classifier: License :: OSI Approved :: Apache Software License
Classifier: Programming Language :: Python :: 3.8
Classifier: Programming Language :: Python :: 3.9
Classifier: Topic :: Scientific/Engineering :: Hydrology
Requires-Dist: booklet
Requires-Dist: geopandas
Requires-Dist: orjson
Requires-Dist: pandas
Requires-Dist: scipy
Requires-Dist: smart-open
Requires-Dist: zstandard
